VerilogSource/PreFabALU+RF+BS/BarrelShifter.v
module BarrelShifter(input [31:0] Rs,Rm,IR,input SR29_IN,output SR29_OUT,output [31:0] Out);
/* 
Data processing immediate IR[27:25] == 000 & IR[4] = 0/ IR[6:5] Shiftype / IR[11:7] Shift Amount/ Shift val Rm
Data register shift IR[27:25] == 000 / IR[6:5] Shiftype / Rs Shift Amount/ Shift val Rm
Data processing immediate IR[27:25] == 001 / ROR Shiftype / IR[11:7] Shift Amount / Shift val IR[7:0]
Load/Store immediate IR[27:25] == 010
Load/Store register offset IR[27:25] == 011
branch and branch with link IR[27:25] == 101
*/
reg [31:0] shiftVal,shiftAmount;
reg [1:0]  shiftType;
always@(IR or Rm or Rs or SR29_IN)
begin 
	case(IR[27:25])
		3'b000:
			begin
				if(!IR[4])//Immediate Rs
					begin
						$display("Immediate Rm");
						shiftVal = Rm;
						shiftAmount = IR[11:7];
						shiftType = IR[6:5];
					end
				else
					begin
						$display("Registe rm");	// Registe rs		
						shiftVal = Rm;
						shiftAmount = Rs[5:0];
						shiftType = IR[6:5];
					end
			end
		3'b001:
			begin//Imediate IR[7:0]
				$display("Imediate IR[7:0]");
				shiftVal = IR[7:0];
				shiftAmount = IR[11:8]*2;
				shiftType = 2'b11;
			end
		3'b010:
			begin//Imediate IR[7:0]
				$display("Load/Store-Immediate Rm");
				_Out = {IR[11],IR[11],IR[11],IR[11],IR[11],
						IR[11],IR[11],IR[11],IR[11],IR[11],
						IR[11],IR[11],IR[11],IR[11],IR[11],
						IR[11],IR[11],IR[11],IR[11],IR[11],
						IR[11:0]};
			end
		3'b011:
			begin//Imediate IR[7:0]
				$display("Load/Store-offsett/index Rm");
				shiftVal = Rm;
				shiftAmount =  IR[11:7];
				shiftType = IR[6:5];
			end
		3'b101:
			begin//branch 
				$display("Branch");
				_Out = 4*{IR[23],IR[23],IR[23],IR[23],IR[23],IR[23],IR[23],IR[23],IR[23],IR[23:0]};
			end
	endcase
end

reg [32:0] temp,temp2;
reg [31:0] _Out;
reg _SR29_OUT;
integer i=0;

assign Out = _Out;
assign SR29_OUT = _SR29_OUT;

always@(*)
begin
	case(shiftType)
		2'b00:
			begin
				$display("LSL");
				if(shiftAmount==32)
					_Out = 0 ;
				else if (shiftAmount>=33)
					{_SR29_OUT,_Out} = 0 ;
				else begin
				temp = {SR29_IN,shiftVal };
				temp2 = 0;				
				for(i = 0; i <= 32 - shiftAmount[4:0] ;i = i + 1) begin
						temp2[32-i] = temp[32-i-shiftAmount[4:0] ] ; 
				end
				{_SR29_OUT,_Out} = temp2; 
				end
			end
		2'b01:	
			begin
				$display("LSR");
				if(shiftAmount==32)
					_Out = 0 ;
				else if (shiftAmount>=33)
					{_SR29_OUT,_Out} = 0 ;
				else begin
				temp = {shiftVal,SR29_IN};
				temp2 = 0;				
				for(i = 0; i <= 32-shiftAmount[4:0] ;i = i + 1) begin
						temp2[i] = temp[i+shiftAmount[4:0] ] ; 
				end
				{_Out,_SR29_OUT} = temp2; 
				end
			end
		2'b10:
			begin 
				$display("ASR");
				if(shiftAmount==32)
					begin
						_Out = {shiftVal[31],shiftVal[31],shiftVal[31],shiftVal[31],shiftVal[31],
							 shiftVal[31],shiftVal[31],shiftVal[31],shiftVal[31],shiftVal[31],
							 shiftVal[31],shiftVal[31],shiftVal[31],shiftVal[31],shiftVal[31],
							 shiftVal[31],shiftVal[31],shiftVal[31],shiftVal[31],shiftVal[31],
							 shiftVal[31],shiftVal[31],shiftVal[31],shiftVal[31],shiftVal[31],
							 shiftVal[31],shiftVal[31],shiftVal[31],shiftVal[31],shiftVal[31],
							 shiftVal[31]};	
					end
				else if (shiftAmount>=33)
					begin
						{_SR29_OUT,_Out} = {shiftVal[31],shiftVal[31],shiftVal[31],shiftVal[31],shiftVal[31],
							 shiftVal[31],shiftVal[31],shiftVal[31],shiftVal[31],shiftVal[31],
							 shiftVal[31],shiftVal[31],shiftVal[31],shiftVal[31],shiftVal[31],
							 shiftVal[31],shiftVal[31],shiftVal[31],shiftVal[31],shiftVal[31],
							 shiftVal[31],shiftVal[31],shiftVal[31],shiftVal[31],shiftVal[31],
							 shiftVal[31],shiftVal[31],shiftVal[31],shiftVal[31],shiftVal[31],
							 shiftVal[31],shiftVal[31]};
					end
				else begin
				temp = {shiftVal,SR29_IN };
				//Lazy to encode in loop
				temp2 = {shiftVal[31],shiftVal[31],shiftVal[31],shiftVal[31],shiftVal[31],
						 shiftVal[31],shiftVal[31],shiftVal[31],shiftVal[31],shiftVal[31],
						 shiftVal[31],shiftVal[31],shiftVal[31],shiftVal[31],shiftVal[31],
						 shiftVal[31],shiftVal[31],shiftVal[31],shiftVal[31],shiftVal[31],
						 shiftVal[31],shiftVal[31],shiftVal[31],shiftVal[31],shiftVal[31],
						 shiftVal[31],shiftVal[31],shiftVal[31],shiftVal[31],shiftVal[31],
						 shiftVal[31],shiftVal[31]};				
				for(i = 0; i <= 32-shiftAmount[4:0] ;i = i + 1) begin
						temp2[i] = temp[i+shiftAmount[4:0] ] ; 
				end
				{_Out,_SR29_OUT} = temp2; 
				end
			end
		2'b11:
			begin
				$display("ROR");
				temp = {shiftVal,SR29_IN};
				temp2 = temp;				
				for(i = 0; i <= 32 ;i = i + 1) begin
						temp2[i] = temp[(i+shiftAmount[4:0])%33] ; 
						$display("[%3d]=[%3d]",i,(i+shiftAmount[4:0])%33);
				end
				{_Out,_SR29_OUT} = temp2; 
			end
	endcase
end

endmodule

VerilogSouce/BarrelShifter/BarrelShifterTestBench.v
module BarrelShifterTestBench;

parameter sim_time = 750*2; // Num of Cycles * 2 
reg [31:0] Rs,Rm,IR;
reg SR29_IN;
wire SR29_OUT;
wire [31:0] Out;
//BarrelShifter(input [31] Rs,Rm,IR,input SR29_IN,output SR29_OUT,output [31:0] Out);
BarrelShifter bs(Rs,Rm,IR,SR29_IN,SR29_OUT,Out);


initial fork
	Rs=0;Rm=0;IR=0;SR29_IN=0;
	#1 Rs=1;#1 Rm=2;#1 IR[4]=1;#1 SR29_IN=0;
	#2 Rs=1;#2 Rm=4; #2 SR29_IN=0;
	#3 Rs=1;#3 Rm=8; #3 SR29_IN=0;
	#4 Rs=8;#4 Rm=1; #4 SR29_IN=0;
	#10 Rs=1;#10 Rm=2;#10 IR[6:5]=1;#10 SR29_IN=0;
	#11 Rs=1;#11 Rm=4; #11 SR29_IN=0;
	#12 Rs=1;#12 Rm=8; #12 SR29_IN=0;
	#13 Rs=8;#13 Rm=1; #13 SR29_IN=0;
	#20 Rs=1;#20 Rm=2;#20 IR[6:5]=2;#20 SR29_IN=0;
	#21 Rs=1;#21 Rm=4; #21 SR29_IN=0;
	#22 Rs=1;#22 Rm=8; #22 SR29_IN=0;
	#23 Rs=8;#23 Rm=1; #23 SR29_IN=0;
	#24 Rs=8;#24 Rm=32'hF0000001; #24 SR29_IN=0;
	#30 Rs=1;#30 Rm=2;#30 IR[6:5]=3;#30 SR29_IN=0;
	#31 Rs=1;#31 Rm=4; #31 SR29_IN=0;
	#32 Rs=1;#32 Rm=8; #32 SR29_IN=0;
	#33 Rs=8;#33 Rm=1; #33 SR29_IN=0;
	#34 Rs=8;#34 Rm=32'hF0000001; #34 SR29_IN=0;
	#40 IR[11:8]=0;#40 IR[7:0]=0;#40 IR[27:25]=1;#40 IR[4]=0;#40 SR29_IN=0;
	#41 IR[11:8]=8;#41 IR[7:0] =1 ; #41 SR29_IN=0;
	#50 Rs=0;#50 Rm=0;#50 IR[27:25]=3'b101;#50 SR29_IN=0;
join
	
initial #sim_time $finish; 

initial begin
	$dumpfile("BarrelShifterTestBench.vcd");
	$dumpvars(0,BarrelShifterTestBench);
	$display(" Test Results" );
	$monitor("Rs=%8h,Rm=%8h,IR=%8h,Out=%8h,SR29_IN=%1b,SR29_OUT=%1b",Rs,Rm,IR,Out,SR29_IN,SR29_OUT);
end

endmodule
//iverilog BarrelShifter.v BarrelShifterTestBench.v
//reference 1 http://infocenter.arm.com/help/index.jsp?topic=/com.arm.doc.dui0497a/CIHDDCIF.html

VerilogSource/BarrelShifter/BarrelShifterTestBench.vcd
$date
	Thu Mar 24 15:39:05 2016
$end
$version
	Icarus Verilog
$end
$timescale
	1s
$end
$scope module BarrelShifterTestBench $end
$var wire 1 ! SR29_OUT $end
$var wire 32 " Out [31:0] $end
$var reg 32 # IR [31:0] $end
$var reg 32 $ Rm [31:0] $end
$var reg 32 % Rs [31:0] $end
$var reg 1 & SR29_IN $end
$scope module bs $end
$var wire 32 ' IR [31:0] $end
$var wire 32 ( Out [31:0] $end
$var wire 32 ) Rm [31:0] $end
$var wire 32 * Rs [31:0] $end
$var wire 1 & SR29_IN $end
$var wire 1 ! SR29_OUT $end
$var reg 32 + _Out [31:0] $end
$var reg 1 , _SR29_OUT $end
$var reg 32 - shiftAmount [31:0] $end
$var reg 2 . shiftType [1:0] $end
$var reg 32 / shiftVal [31:0] $end
$var reg 33 0 temp [32:0] $end
$var reg 33 1 temp2 [32:0] $end
$var integer 32 2 i [31:0] $end
$upscope $end
$upscope $end
$enddefinitions $end
#0
$dumpvars
b100001 2
b0 1
b0 0
b0 /
b0 .
b0 -
0,
b0 +
b0 *
b0 )
b0 (
b0 '
0&
b0 %
b0 $
b0 #
b0 "
0!
$end
#1
b100 "
b100 (
b100 +
b100 1
b100000 2
b10 0
b1 -
b10 /
b1 %
b1 *
b10 $
b10 )
b10000 #
b10000 '
#2
b1000 "
b1000 (
b1000 +
b100000 2
b1000 1
b100 0
b100 /
b100 $
b100 )
#3
b10000 "
b10000 (
b10000 +
b100000 2
b10000 1
b1000 0
b1000 /
b1000 $
b1000 )
#4
b100000000 "
b100000000 (
b100000000 +
b11001 2
b100000000 1
b1 0
b1000 -
b1 /
b1000 %
b1000 *
b1 $
b1 )
#10
b1 "
b1 (
b1 +
b100000 2
b10 1
b100 0
b1 .
b1 -
b10 /
b1 %
b1 *
b10 $
b10 )
b110000 #
b110000 '
#11
b10 "
b10 (
b10 +
b100000 2
b100 1
b1000 0
b100 /
b100 $
b100 )
#12
b100 "
b100 (
b100 +
b100000 2
b1000 1
b10000 0
b1000 /
b1000 $
b1000 )
#13
b0 "
b0 (
b0 +
b11001 2
b0 1
b10 0
b1000 -
b1 /
b1000 %
b1000 *
b1 $
b1 )
#20
b1 "
b1 (
b1 +
b10 1
b100000 2
b100 0
b10 .
b1 -
b10 /
b1 %
b1 *
b10 $
b10 )
b1010000 #
b1010000 '
#21
b10 "
b10 (
b10 +
b100000 2
b100 1
b1000 0
b100 /
b100 $
b100 )
#22
b100 "
b100 (
b100 +
b100000 2
b1000 1
b10000 0
b1000 /
b1000 $
b1000 )
#23
b0 "
b0 (
b0 +
b11001 2
b0 1
b10 0
b1000 -
b1 /
b1000 %
b1000 *
b1 $
b1 )
#24
b1111111111100000000000000000000 "
b1111111111100000000000000000000 (
b1111111111100000000000000000000 +
b11001 2
b11111111111000000000000000000000 1
b111100000000000000000000000000010 0
b11110000000000000000000000000001 /
b11110000000000000000000000000001 $
b11110000000000000000000000000001 )
#30
b1 "
b1 (
b1 +
b100001 2
b10 1
b100 0
b11 .
b1 -
b10 /
b1 %
b1 *
b10 $
b10 )
b1110000 #
b1110000 '
#31
b10 "
b10 (
b10 +
b100001 2
b100 1
b1000 0
b100 /
b100 $
b100 )
#32
b100 "
b100 (
b100 +
b100001 2
b1000 1
b10000 0
b1000 /
b1000 $
b1000 )
#33
b10000000000000000000000000 "
b10000000000000000000000000 (
b10000000000000000000000000 +
b100001 2
b100000000000000000000000000 1
b10 0
b1000 -
b1 /
b1000 %
b1000 *
b1 $
b1 )
#34
b10111100000000000000000000 "
b10111100000000000000000000 (
b10111100000000000000000000 +
b100001 2
b101111000000000000000000000 1
b111100000000000000000000000000010 0
b11110000000000000000000000000001 /
b11110000000000000000000000000001 $
b11110000000000000000000000000001 )
#40
b0 "
b0 (
b0 +
b100001 2
b0 1
b0 0
b0 -
b0 /
b10000000000000000000000000 #
b10000000000000000000000000 '
#41
b100000000000000000 "
b100000000000000000 (
b100000000000000000 +
b100001 2
b1000000000000000000 1
b10 0
b10000 -
b1 /
b10000000000000100000000001 #
b10000000000000100000000001 '
#50
b10000000000100 "
b10000000000100 (
b10000000000100 +
b0 %
b0 *
b0 $
b0 )
b1010000000000000100000000001 #
b1010000000000000100000000001 '
