VerilogSource/ControlUnit+ALU/Decoder4x16.v
module Decoder4x16(input [3:0] IN,output reg [15:0] OUT);
integer i=0;
always@(IN)
begin
	for(i=0;i<=15;i=i+1)
	begin
		OUT[i] = 0;
	end
	OUT[IN]=1;
end 
endmodule

VerilogSouce/Decoder4x16/DecoderTestBench.v
module DecoderTestBench;

parameter sim_time = 750*2; // Num of Cycles * 2 

reg [3:0] in_test;
wire[15:0] out_test;

Decoder4x16 dec(.IN(in_test),.OUT(out_test));


initial fork
	 in_test = 0;
	 #1 in_test = 1;
	 #2 in_test = 2;
	 #3 in_test = 3;
	 #4 in_test = 4;
	 #5 in_test = 5;
	 #6 in_test = 6;
	 #7 in_test = 7;
	 #8 in_test = 8;
	 #9 in_test = 9;
	 #10 in_test = 10;
	 #11 in_test = 11;
	 #12 in_test = 12;
	 #13 in_test = 13;
	 #14 in_test = 14;
	 #15 in_test = 15;
join


initial #sim_time $finish;           //Especifica cuando termina la simulacion



initial begin
	$dumpfile("DecoderTestBench.vcd");
	$dumpvars(0,DecoderTestBench);
	$display(" Test Results" );                  // imprime header
	$monitor("Time = %3d,IN = %3d,OUT=%4b",$time,in_test,out_test);
end

endmodule
//iverilog Decoder4x16.v DecoderTestBench.v
//vvp a.out
//gtkwave DecoderTestBench.vcd

VerilogSouce/Decoder4x16/DecoderTestBench.vcd
$date
	Mon Feb 08 20:46:49 2016
$end
$version
	Icarus Verilog
$end
$timescale
	1s
$end
$scope module DecoderTestBench $end
$var wire 16 ! out_test [15:0] $end
$var reg 4 " in_test [3:0] $end
$scope module dec $end
$var wire 4 # IN [3:0] $end
$var reg 16 $ OUT [15:0] $end
$var integer 32 % i [31:0] $end
$upscope $end
$upscope $end
$enddefinitions $end
#0
$dumpvars
b10000 %
b1 $
b0 #
b0 "
b1 !
$end
#1
b10 !
b10 $
b10000 %
b1 "
b1 #
#2
b100 !
b100 $
b10000 %
b10 "
b10 #
#3
b1000 !
b1000 $
b10000 %
b11 "
b11 #
#4
b10000 !
b10000 $
b10000 %
b100 "
b100 #
#5
b100000 !
b100000 $
b10000 %
b101 "
b101 #
#6
b1000000 !
b1000000 $
b10000 %
b110 "
b110 #
#7
b10000000 !
b10000000 $
b10000 %
b111 "
b111 #
#8
b100000000 !
b100000000 $
b10000 %
b1000 "
b1000 #
#9
b1000000000 !
b1000000000 $
b10000 %
b1001 "
b1001 #
#10
b10000000000 !
b10000000000 $
b10000 %
b1010 "
b1010 #
#11
b100000000000 !
b100000000000 $
b10000 %
b1011 "
b1011 #
#12
b1000000000000 !
b1000000000000 $
b10000 %
b1100 "
b1100 #
#13
b10000000000000 !
b10000000000000 $
b10000 %
b1101 "
b1101 #
#14
b100000000000000 !
b100000000000000 $
b10000 %
b1110 "
b1110 #
#15
b1000000000000000 !
b1000000000000000 $
b10000 %
b1111 "
b1111 #
