VerilogSource/EmbededSystem/Register.v
module Register(input [31:0] IN,input Clk, Reset,Load,output [31:0] OUT);
reg [31:0] d;
assign OUT = d;
always@(negedge Clk)
begin
	if(Load)
		d=IN;
end

always@(Reset)
	d=0;

endmodule

VerilogSource/Register/RegisterTestBench2.v
module RegisterTestBench2;

parameter sim_time = 750*2; // Num of Cycles * 2 

reg [31:0] In;
reg Clk,Reset;
reg[15:0] Load;
wire[31:0] Out[15:0];

generate
  genvar i;
  for (i=0; i<=15; i=i+1) begin : registers
    Register test_reg(.IN(In),
				  .Clk(Clk),
				  .Reset(Reset),
				  .Load(Load[i]),
				  .OUT(Out[i]));
  end
endgenerate

integer j=0;

initial fork
	//Cycle 1 == Set
	//Clk = 0
	In=0;Reset=1;Clk = 0;
	for(j=0;j<=15;j=j+1)
	begin
		Load[j]=0;
	end
	#1 //Clk = 1 
	In=1;
	#1 Reset=0;
	#1 Load[0]=1; // always load on tick after for loop
	//#2 Clk = 0 Cycle 2
	#3 for(j=0;j<=15;j=j+1)
	begin
		Load[j]=0;
	end
	#4 Load[1]=1;
	#5 In=2;
	#5 //Clk =0 Cycle 3
	for(j=0;j<=15;j=j+1)
	begin
		Load[j]=0;
	end
	#6 Load[2]=1;
	#6 In=3;
	#7 //Clk =0 Cycle 4
	for(j=0;j<=15;j=j+1)
	begin
		Load[j]=0;
	end
	#8 Load[3]=1;
	#8 In=4;
	#9 //Clk =0 Cycle 5
	for(j=0;j<=15;j=j+1)
	begin
		Load[j]=0;
	end
	#10 Load[4]=1;
	#10 In=5;
	#11 //Clk = 0 Cycle 6
	for(j=0;j<=15;j=j+1)
	begin
		Load[j]=0;
	end
	#12 Load[5]=1;
	#12 In=6;
	#13 //Clk = 0 Cycle 7
	for(j=0;j<=15;j=j+1)
	begin
		Load[j]=0;
	end
	#14 Load[6]=1;
	#14 In=7;
	#15 //Clk = 0 Cycle 8
	for(j=0;j<=15;j=j+1)
	begin
		Load[j]=0;
	end
	#16 Load[7]=1;
	#16 In=8;
	#17 //Clk = 0 Cycle 9
	for(j=0;j<=15;j=j+1)
	begin
		Load[j]=0;
	end
	#18 Load[8]=1;
	#18 In=9;
	#19 //Clk = 0 Cycle 10
	for(j=0;j<=15;j=j+1)
	begin
		Load[j]=0;
	end
	#20 Load[9]=1;
	#20 In=10;
	#21 //Clk = 0 Cycle 11
	for(j=0;j<=15;j=j+1)
	begin
		Load[j]=0;
	end
	#22 Load[10]=1;
	#22 In=11;
	#23 //Clk = 0 Cycle 12
	for(j=0;j<=15;j=j+1)
	begin
		Load[j]=0;
	end
	#24 Load[11]=1;
	#24 In=12;
	#25 //Clk = 0 Cycle 13
	for(j=0;j<=15;j=j+1)
	begin
		Load[j]=0;
	end
	#26 Load[12]=1;
	#26 In=13;
	#27 //Clk = 0 Cycle 13
	for(j=0;j<=15;j=j+1)
	begin
		Load[j]=0;
	end
	#28 Load[13]=1;
	#28 In=14;
	#29 //Clk = 0 Cycle 14
	for(j=0;j<=15;j=j+1)
	begin
		Load[j]=0;
	end
	#30 Load[14]=1;
	#30 In=15;
	#31 //Clk = 0 Cycle 15
	for(j=0;j<=15;j=j+1)
	begin
		Load[j]=0;
	end
	#32 Load[15]=1;
	#32 In=16;
join

always 
	#1 Clk = ~Clk;
	
initial #sim_time $finish;           //Especifica cuando termina la simulacion



initial begin
	$dumpfile("RegisterTestBench2.vcd");
	$dumpvars(0,RegisterTestBench2);
	$display(" Test Results" );                  // imprime header
	$monitor("T = %3d,Clk = %3d,In = %3d,Reset = %3d,Load[0] = %3d,Load[1] = %3d,Load[2] = %3d,Load[3] = %3d,Load[4] = %3d,Load[5] = %3d,Load[6] = %3d,Load[7] = %3d,Load[8] = %3d,Load[9] = %3d,Load[10] = %3d,Load[11] = %3d,Load[12] = %3d,Load[13] = %3d,Load[14] = %3d,Load[15] = %3d,Out[0] = %3d,Out[1] = %3d,Out[2] = %3d,Out[3] = %3d,Out[4] = %3d,Out[5] = %3d,Out[6] = %3d,Out[7] = %3d,Out[8] = %3d,Out[9] = %3d,Out[10] = %3d,Out[11] = %3d,Out[12] = %3d,Out[13] = %3d,Out[14] = %3d,Out[15] = %3d",$time,Clk,In,Reset,Load[0],Load[1],Load[2],Load[3],Load[4],Load[5],Load[6],Load[7],Load[8],Load[9],Load[10],Load[11],Load[12],Load[13],Load[14],Load[15],Out[0],Out[1],Out[2],Out[3],Out[4],Out[5],Out[6],Out[7],Out[8],Out[9],Out[10],Out[11],Out[12],Out[13],Out[14],Out[15]);  //imprime se~ales
end

endmodule
//iverilog Register.v RegisterTestBench2.v
//gtkwave RegisterTestBench2.vcd

VerilogSource/Register/RegisterTestBench2.vcd
$date
	Sat Feb 13 16:05:51 2016
$end
$version
	Icarus Verilog
$end
$timescale
	1s
$end
$scope module RegisterTestBench2 $end
$var reg 1 ! Clk $end
$var reg 32 " In [31:0] $end
$var reg 16 # Load [15:0] $end
$var reg 1 $ Reset $end
$var integer 32 % j [31:0] $end
$scope begin registers[0] $end
$scope module test_reg $end
$var wire 1 ! Clk $end
$var wire 32 & IN [31:0] $end
$var wire 1 ' Load $end
$var wire 32 ( OUT [31:0] $end
$var wire 1 $ Reset $end
$var reg 32 ) d [31:0] $end
$upscope $end
$upscope $end
$scope begin registers[1] $end
$scope module test_reg $end
$var wire 1 ! Clk $end
$var wire 32 * IN [31:0] $end
$var wire 1 + Load $end
$var wire 32 , OUT [31:0] $end
$var wire 1 $ Reset $end
$var reg 32 - d [31:0] $end
$upscope $end
$upscope $end
$scope begin registers[2] $end
$scope module test_reg $end
$var wire 1 ! Clk $end
$var wire 32 . IN [31:0] $end
$var wire 1 / Load $end
$var wire 32 0 OUT [31:0] $end
$var wire 1 $ Reset $end
$var reg 32 1 d [31:0] $end
$upscope $end
$upscope $end
$scope begin registers[3] $end
$scope module test_reg $end
$var wire 1 ! Clk $end
$var wire 32 2 IN [31:0] $end
$var wire 1 3 Load $end
$var wire 32 4 OUT [31:0] $end
$var wire 1 $ Reset $end
$var reg 32 5 d [31:0] $end
$upscope $end
$upscope $end
$scope begin registers[4] $end
$scope module test_reg $end
$var wire 1 ! Clk $end
$var wire 32 6 IN [31:0] $end
$var wire 1 7 Load $end
$var wire 32 8 OUT [31:0] $end
$var wire 1 $ Reset $end
$var reg 32 9 d [31:0] $end
$upscope $end
$upscope $end
$scope begin registers[5] $end
$scope module test_reg $end
$var wire 1 ! Clk $end
$var wire 32 : IN [31:0] $end
$var wire 1 ; Load $end
$var wire 32 < OUT [31:0] $end
$var wire 1 $ Reset $end
$var reg 32 = d [31:0] $end
$upscope $end
$upscope $end
$scope begin registers[6] $end
$scope module test_reg $end
$var wire 1 ! Clk $end
$var wire 32 > IN [31:0] $end
$var wire 1 ? Load $end
$var wire 32 @ OUT [31:0] $end
$var wire 1 $ Reset $end
$var reg 32 A d [31:0] $end
$upscope $end
$upscope $end
$scope begin registers[7] $end
$scope module test_reg $end
$var wire 1 ! Clk $end
$var wire 32 B IN [31:0] $end
$var wire 1 C Load $end
$var wire 32 D OUT [31:0] $end
$var wire 1 $ Reset $end
$var reg 32 E d [31:0] $end
$upscope $end
$upscope $end
$scope begin registers[8] $end
$scope module test_reg $end
$var wire 1 ! Clk $end
$var wire 32 F IN [31:0] $end
$var wire 1 G Load $end
$var wire 32 H OUT [31:0] $end
$var wire 1 $ Reset $end
$var reg 32 I d [31:0] $end
$upscope $end
$upscope $end
$scope begin registers[9] $end
$scope module test_reg $end
$var wire 1 ! Clk $end
$var wire 32 J IN [31:0] $end
$var wire 1 K Load $end
$var wire 32 L OUT [31:0] $end
$var wire 1 $ Reset $end
$var reg 32 M d [31:0] $end
$upscope $end
$upscope $end
$scope begin registers[10] $end
$scope module test_reg $end
$var wire 1 ! Clk $end
$var wire 32 N IN [31:0] $end
$var wire 1 O Load $end
$var wire 32 P OUT [31:0] $end
$var wire 1 $ Reset $end
$var reg 32 Q d [31:0] $end
$upscope $end
$upscope $end
$scope begin registers[11] $end
$scope module test_reg $end
$var wire 1 ! Clk $end
$var wire 32 R IN [31:0] $end
$var wire 1 S Load $end
$var wire 32 T OUT [31:0] $end
$var wire 1 $ Reset $end
$var reg 32 U d [31:0] $end
$upscope $end
$upscope $end
$scope begin registers[12] $end
$scope module test_reg $end
$var wire 1 ! Clk $end
$var wire 32 V IN [31:0] $end
$var wire 1 W Load $end
$var wire 32 X OUT [31:0] $end
$var wire 1 $ Reset $end
$var reg 32 Y d [31:0] $end
$upscope $end
$upscope $end
$scope begin registers[13] $end
$scope module test_reg $end
$var wire 1 ! Clk $end
$var wire 32 Z IN [31:0] $end
$var wire 1 [ Load $end
$var wire 32 \ OUT [31:0] $end
$var wire 1 $ Reset $end
$var reg 32 ] d [31:0] $end
$upscope $end
$upscope $end
$scope begin registers[14] $end
$scope module test_reg $end
$var wire 1 ! Clk $end
$var wire 32 ^ IN [31:0] $end
$var wire 1 _ Load $end
$var wire 32 ` OUT [31:0] $end
$var wire 1 $ Reset $end
$var reg 32 a d [31:0] $end
$upscope $end
$upscope $end
$scope begin registers[15] $end
$scope module test_reg $end
$var wire 1 ! Clk $end
$var wire 32 b IN [31:0] $end
$var wire 1 c Load $end
$var wire 32 d OUT [31:0] $end
$var wire 1 $ Reset $end
$var reg 32 e d [31:0] $end
$upscope $end
$upscope $end
$upscope $end
$enddefinitions $end
#0
$dumpvars
b0 e
b0 d
0c
b0 b
b0 a
b0 `
0_
b0 ^
b0 ]
b0 \
0[
b0 Z
b0 Y
b0 X
0W
b0 V
b0 U
b0 T
0S
b0 R
b0 Q
b0 P
0O
b0 N
b0 M
b0 L
0K
b0 J
b0 I
b0 H
0G
b0 F
b0 E
b0 D
0C
b0 B
b0 A
b0 @
0?
b0 >
b0 =
b0 <
0;
b0 :
b0 9
b0 8
07
b0 6
b0 5
b0 4
03
b0 2
b0 1
b0 0
0/
b0 .
b0 -
b0 ,
0+
b0 *
b0 )
b0 (
0'
b0 &
b10000 %
1$
b0 #
b0 "
0!
$end
#1
1'
1!
b1 "
b1 &
b1 *
b1 .
b1 2
b1 6
b1 :
b1 >
b1 B
b1 F
b1 J
b1 N
b1 R
b1 V
b1 Z
b1 ^
b1 b
0$
b1 #
#2
b1 (
b1 )
0!
#3
0'
1!
b0 #
b10000 %
#4
b1 ,
b1 -
1+
0!
b10 #
#5
0+
1!
b10 "
b10 &
b10 *
b10 .
b10 2
b10 6
b10 :
b10 >
b10 B
b10 F
b10 J
b10 N
b10 R
b10 V
b10 Z
b10 ^
b10 b
b0 #
b10000 %
#6
b11 0
b11 1
1/
0!
b100 #
b11 "
b11 &
b11 *
b11 .
b11 2
b11 6
b11 :
b11 >
b11 B
b11 F
b11 J
b11 N
b11 R
b11 V
b11 Z
b11 ^
b11 b
#7
0/
1!
b0 #
b10000 %
#8
b100 4
b100 5
13
0!
b1000 #
b100 "
b100 &
b100 *
b100 .
b100 2
b100 6
b100 :
b100 >
b100 B
b100 F
b100 J
b100 N
b100 R
b100 V
b100 Z
b100 ^
b100 b
#9
03
1!
b0 #
b10000 %
#10
b101 8
b101 9
17
0!
b10000 #
b101 "
b101 &
b101 *
b101 .
b101 2
b101 6
b101 :
b101 >
b101 B
b101 F
b101 J
b101 N
b101 R
b101 V
b101 Z
b101 ^
b101 b
#11
07
1!
b0 #
b10000 %
#12
b110 <
b110 =
1;
0!
b100000 #
b110 "
b110 &
b110 *
b110 .
b110 2
b110 6
b110 :
b110 >
b110 B
b110 F
b110 J
b110 N
b110 R
b110 V
b110 Z
b110 ^
b110 b
#13
0;
1!
b0 #
b10000 %
#14
b111 @
b111 A
1?
0!
b1000000 #
b111 "
b111 &
b111 *
b111 .
b111 2
b111 6
b111 :
b111 >
b111 B
b111 F
b111 J
b111 N
b111 R
b111 V
b111 Z
b111 ^
b111 b
#15
0?
1!
b0 #
b10000 %
#16
b1000 D
b1000 E
1C
0!
b10000000 #
b1000 "
b1000 &
b1000 *
b1000 .
b1000 2
b1000 6
b1000 :
b1000 >
b1000 B
b1000 F
b1000 J
b1000 N
b1000 R
b1000 V
b1000 Z
b1000 ^
b1000 b
#17
0C
1!
b0 #
b10000 %
#18
b1001 H
b1001 I
1G
0!
b100000000 #
b1001 "
b1001 &
b1001 *
b1001 .
b1001 2
b1001 6
b1001 :
b1001 >
b1001 B
b1001 F
b1001 J
b1001 N
b1001 R
b1001 V
b1001 Z
b1001 ^
b1001 b
#19
0G
1!
b0 #
b10000 %
#20
b1010 L
b1010 M
1K
0!
b1000000000 #
b1010 "
b1010 &
b1010 *
b1010 .
b1010 2
b1010 6
b1010 :
b1010 >
b1010 B
b1010 F
b1010 J
b1010 N
b1010 R
b1010 V
b1010 Z
b1010 ^
b1010 b
#21
0K
1!
b0 #
b10000 %
#22
b1011 P
b1011 Q
1O
0!
b10000000000 #
b1011 "
b1011 &
b1011 *
b1011 .
b1011 2
b1011 6
b1011 :
b1011 >
b1011 B
b1011 F
b1011 J
b1011 N
b1011 R
b1011 V
b1011 Z
b1011 ^
b1011 b
#23
0O
1!
b0 #
b10000 %
#24
b1100 T
b1100 U
1S
0!
b100000000000 #
b1100 "
b1100 &
b1100 *
b1100 .
b1100 2
b1100 6
b1100 :
b1100 >
b1100 B
b1100 F
b1100 J
b1100 N
b1100 R
b1100 V
b1100 Z
b1100 ^
b1100 b
#25
0S
1!
b0 #
b10000 %
#26
b1101 X
b1101 Y
1W
0!
b1000000000000 #
b1101 "
b1101 &
b1101 *
b1101 .
b1101 2
b1101 6
b1101 :
b1101 >
b1101 B
b1101 F
b1101 J
b1101 N
b1101 R
b1101 V
b1101 Z
b1101 ^
b1101 b
#27
0W
1!
b0 #
b10000 %
#28
b1110 \
b1110 ]
1[
0!
b10000000000000 #
b1110 "
b1110 &
b1110 *
b1110 .
b1110 2
b1110 6
b1110 :
b1110 >
b1110 B
b1110 F
b1110 J
b1110 N
b1110 R
b1110 V
b1110 Z
b1110 ^
b1110 b
#29
0[
1!
b0 #
b10000 %
#30
b1111 `
b1111 a
1_
0!
b100000000000000 #
b1111 "
b1111 &
b1111 *
b1111 .
b1111 2
b1111 6
b1111 :
b1111 >
b1111 B
b1111 F
b1111 J
b1111 N
b1111 R
b1111 V
b1111 Z
b1111 ^
b1111 b
#31
0_
1!
b0 #
b10000 %
#32
b10000 d
b10000 e
1c
0!
b1000000000000000 #
b10000 "
b10000 &
b10000 *
b10000 .
b10000 2
b10000 6
b10000 :
b10000 >
b10000 B
b10000 F
b10000 J
b10000 N
b10000 R
b10000 V
b10000 Z
b10000 ^
b10000 b
