VerilogSouce/PreFabALU+RF+BS/Buffer32_32.v
module Buffer32_32(input [31:0] IN,input Store,output [31:0] OUT);
assign OUT = Store ? IN : 32'bZ;
endmodule

VerilogSource/Register2Buffers/Register2.v
module Register2(input [31:0] IN,IN2,input Clk, Reset,Load,Load2,output [31:0] OUT);
reg [31:0] d;
assign OUT = d;
always@(negedge Clk)
begin
	if(Load)
		d=IN;
	else if(Load2)
		d=IN2;
end

always@(Reset)
	d=0;

endmodule

VerilogSource/Register2Buffers/Register2Buff.v
module Register2Buff(inout [31:0] IN,IN2,input Clk, Reset,Load,Load2,Store,Store2);
wire [31:0] _OUT;
//module Register2(input [31:0] IN,IN2,input Clk, Reset,Load,Load2,output [31:0] OUT);
Register2 register( IN,IN2, Clk, Reset,Load,Load2, _OUT);
//Buffer32_32(input [31:0] IN,input Store,output [31:0] OUT);
Buffer32_32 buff1( _OUT, Store, IN);
//Buffer32_32(input [31:0] IN,input Store,output [31:0] OUT);
Buffer32_32 buff2( _OUT, Store2,IN2);
endmodule

VerilogSource/Register2Buffers/RegisterTestBench.v
module RegisterTestBench;

parameter sim_time = 750*2; // Num of Cycles * 2 
wire [31:0] test_in,test_in2;
reg test_clk,test_reset,test_load,test_load2,test_store,test_store2;
reg [31:0] test_in_buff,test_in2_buff;
assign test_in=test_in_buff;
assign test_in2=test_in2_buff;
//Register2Buff(inout [31:0] IN,IN2,input Clk, Reset,Load,Load2,Store,Store2);
Register2Buff register(
			  .IN(test_in),
			  .IN2(test_in2),
			  .Clk(test_clk), 
			  .Reset(test_reset),
			  .Load(test_load),
			  .Load2(test_load2),
			  .Store(test_store),
			  .Store2(test_store2));

initial fork
	test_in_buff = 0 ; test_in2_buff = 0 ; test_clk=0 ; test_reset=1 ; test_load=0 ; test_load2=0 ; test_store=0 ;test_store2=0 ;
	#(1*2) test_in_buff = 1 ; #(1*2) test_in2_buff = 0 ; #(1*2) test_reset=0 ; #(1*2) test_load=1 ; #(1*2) test_load2=0 ; #(1*2) test_store=0 ; #(1*2) test_store2=0 ;
	#(2*2) test_in_buff = 1 ; #(2*2) test_in2_buff = 0 ; #(2*2) test_reset=0 ; #(2*2) test_load=1 ; #(2*2) test_load2=0 ; #(2*2) test_store=0 ; #(2*2) test_store2=0 ;
	#(3*2) test_in_buff = 1 ; #(3*2) test_in2_buff = 0 ; #(3*2) test_reset=0 ; #(3*2) test_load=0 ; #(3*2) test_load2=0 ; #(3*2) test_store=0 ; #(3*2) test_store2=0 ;
	#(4*2) test_in_buff = 0 ; #(4*2) test_in2_buff = 1 ; #(4*2) test_reset=0 ; #(4*2) test_load=0 ; #(4*2) test_load2=1 ; #(4*2) test_store=0 ; #(4*2) test_store2=0 ;
	#(5*2) test_in_buff = 0 ; #(5*2) test_in2_buff = 1 ; #(5*2) test_reset=0 ; #(5*2) test_load=0 ; #(5*2) test_load2=1 ; #(5*2) test_store=0 ; #(5*2) test_store2=0 ;
	#(6*2) test_in_buff = 0 ; #(6*2) test_in2_buff = 1 ; #(6*2) test_reset=0 ; #(6*2) test_load=0 ; #(6*2) test_load2=1 ; #(6*2) test_store=0 ; #(6*2) test_store2=0 ;
	#(7*2) test_in_buff = 1 ; #(7*2) test_in2_buff = 0 ; #(7*2) test_reset=0 ; #(7*2) test_load=0 ; #(7*2) test_load2=1 ; #(7*2) test_store=0 ; #(7*2) test_store2=0 ;
	#(8*2) test_in_buff = 1 ; #(8*2) test_in2_buff = 0 ; #(8*2) test_reset=0 ; #(8*2) test_load=0 ; #(8*2) test_load2=1 ; #(8*2) test_store=0 ; #(8*2) test_store2=0 ;
	#(9*2) test_in_buff = 1 ; #(9*2) test_in2_buff = 0 ; #(9*2) test_reset=0 ; #(9*2) test_load=0 ; #(9*2) test_load2=1 ; #(9*2) test_store=0 ; #(9*2) test_store2=0 ;
	#(10*2) test_in_buff = 0 ; #(10*2) test_in2_buff = 1 ; #(10*2) test_reset=0 ; #(10*2) test_load=1 ; #(10*2) test_load2=0 ; #(10*2) test_store=0 ; #(10*2) test_store2=0 ;
	#(11*2) test_in_buff = 0 ; #(11*2) test_in2_buff = 1 ; #(11*2) test_reset=0 ; #(11*2) test_load=1 ; #(11*2) test_load2=0 ; #(11*2) test_store=0 ; #(11*2) test_store2=0 ;
	#(12*2) test_in_buff = 0 ; #(12*2) test_in2_buff = 1 ; #(12*2) test_reset=0 ; #(12*2) test_load=0 ; #(12*2) test_load2=0 ; #(12*2) test_store=0 ; #(12*2) test_store2=0 ;
	#(13*2) test_in_buff <= 32'bZZZZZZZZZZZZZZZZZZZZZZZZZZZZZZZZ ; #(13*2) test_in2_buff <= 32'bZZZZZZZZZZZZZZZZZZZZZZZZZZZZZZZZ ; #(13*2) test_reset=0 ; #(13*2) test_load=0 ; #(13*2) test_load2=0 ; #(13*2) test_store=1 ; #(13*2) test_store2=0 ;
	#(14*2) test_in_buff <= 32'bZZZZZZZZZZZZZZZZZZZZZZZZZZZZZZZZ ; #(14*2) test_in2_buff <= 32'bZZZZZZZZZZZZZZZZZZZZZZZZZZZZZZZZ; #(14*2) test_reset=0 ; #(14*2) test_load=0 ; #(14*2) test_load2=0 ; #(14*2) test_store=0 ; #(14*2) test_store2=1 ;
join

always 
	#1 test_clk = ~test_clk;
	
initial #sim_time $finish;           //Especifica cuando termina la simulacion



initial begin
	$dumpfile("RegisterTestBench.vcd");
	$dumpvars(0,RegisterTestBench);
	$display(" Test Results" );                  // imprime header
	$monitor("T = %d,test_in = %d,test_in2 = %d,test_clk = %d,test_reset = %d,test_load = %d,test_load2 = %d,test_store = %d,test_store2 = %d",$time,test_in,test_in2,test_clk,test_reset,test_load,test_load2,test_store,test_store2 );  //imprime se~ales
end

endmodule
//iverilog Register2.v Buffer32_32.v Register2Buff.v RegisterTestBench.v
//gtkwave RegisterTestBench.vcd

VerilogSource/Register2Buffers/RegisterTestBench.vcd
$date
	Wed Mar 23 10:59:47 2016
$end
$version
	Icarus Verilog
$end
$timescale
	1s
$end
$scope module RegisterTestBench $end
$var wire 32 ! test_in [31:0] $end
$var wire 32 " test_in2 [31:0] $end
$var reg 1 # test_clk $end
$var reg 32 $ test_in2_buff [31:0] $end
$var reg 32 % test_in_buff [31:0] $end
$var reg 1 & test_load $end
$var reg 1 ' test_load2 $end
$var reg 1 ( test_reset $end
$var reg 1 ) test_store $end
$var reg 1 * test_store2 $end
$scope module register $end
$var wire 1 # Clk $end
$var wire 32 + IN [31:0] $end
$var wire 32 , IN2 [31:0] $end
$var wire 1 & Load $end
$var wire 1 ' Load2 $end
$var wire 1 ( Reset $end
$var wire 1 ) Store $end
$var wire 1 * Store2 $end
$var wire 32 - _OUT [31:0] $end
$scope module buff1 $end
$var wire 32 . OUT [31:0] $end
$var wire 1 ) Store $end
$var wire 32 / IN [31:0] $end
$upscope $end
$scope module buff2 $end
$var wire 32 0 OUT [31:0] $end
$var wire 1 * Store $end
$var wire 32 1 IN [31:0] $end
$upscope $end
$scope module register $end
$var wire 1 # Clk $end
$var wire 32 2 IN [31:0] $end
$var wire 32 3 IN2 [31:0] $end
$var wire 1 & Load $end
$var wire 1 ' Load2 $end
$var wire 1 ( Reset $end
$var wire 32 4 OUT [31:0] $end
$var reg 32 5 d [31:0] $end
$upscope $end
$upscope $end
$upscope $end
$enddefinitions $end
#0
$dumpvars
b0 5
b0 4
b0 3
b0 2
b0 1
b0 0
b0 /
b0 .
b0 -
b0 ,
b0 +
0*
0)
1(
0'
0&
b0 %
b0 $
0#
b0 "
b0 !
$end
#1
1#
#2
b1 -
b1 /
b1 1
b1 4
b1 5
0#
b1 !
b1 +
b1 .
b1 2
b1 %
0(
1&
#3
1#
#4
0#
#5
1#
#6
0#
0&
#7
1#
#8
0#
b0 !
b0 +
b0 .
b0 2
b0 %
b1 "
b1 ,
b1 0
b1 3
b1 $
1'
#9
1#
#10
0#
#11
1#
#12
0#
#13
1#
#14
b0 -
b0 /
b0 1
b0 4
b0 5
0#
b1 !
b1 +
b1 .
b1 2
b1 %
b0 "
b0 ,
b0 0
b0 3
b0 $
#15
1#
#16
0#
#17
1#
#18
0#
#19
1#
#20
0#
b0 !
b0 +
b0 .
b0 2
b0 %
b1 "
b1 ,
b1 0
b1 3
b1 $
1&
0'
#21
1#
#22
0#
#23
1#
#24
0#
0&
#25
1#
#26
bz %
bz "
bz ,
bz 0
bz 3
bz $
0#
1)
#27
1#
#28
bz !
bz +
bz .
bz 2
b0 "
b0 ,
b0 0
b0 3
0#
0)
1*
